{
  "users": [
    {
      "id": "0cbe",
      "username": "Ale",
      "email": "alejca15@gmail.com",
      "password": "1234",
      "admin": true,
      "sede": "el Huerto"
    },
    {
      "id": "84e2",
      "username": "Jose",
      "email": "jose@fwd.com",
      "password": "1234",
      "admin": true,
      "sede": "el Huerto"
    },
    {
      "id": "645e",
      "username": "Juan",
      "email": "j@fwd.com",
      "password": "12321",
      "admin": true,
      "sede": "2"
    },
    {
      "id": "e549",
      "username": "J",
      "email": "js@fwd.com",
      "password": "12321",
      "admin": false,
      "sede": "2"
    },
    {
      "id": "a48a",
      "username": "Nico",
      "email": "n@fwd.com",
      "password": "123",
      "admin": true,
      "sede": "Nosara"
    },
    {
      "id": "0b4f",
      "username": "Nikky",
      "email": "na@fwd.com",
      "password": "123",
      "admin": false,
      "sede": "Nosara"
    }
  ],
  "peticiones": [
    {
      "id": "7f94",
      "nombre": "jenny",
      "sede": "el Huerto",
      "fechaS": "22/08/2024",
      "fechaE": "25/08/2024",
      "codigo": "FV887SF2",
      "estado": "Pendiente"
    },
    {
      "id": "2a66",
      "nombre": "jenny",
      "sede": "el Huerto",
      "fechaS": "22/08/2024",
      "fechaE": "25/08/2024",
      "codigo": "3fa2",
      "estado": "Pendiente"
    }
  ]
}